django_api_gate/__init__.py
django_api_gate/middleware.py
django_api_gate-0.0.7.dist-info/METADATA
django_api_gate-0.0.7.dist-info/WHEEL
django_api_gate-0.0.7.dist-info/top_level.txt
django_api_gate-0.0.7.dist-info/RECORD
