Metadata-Version: 2.4
Name: django-api-gate
Version: 0.0.7
Summary: A middleware to monetize Django APIs with Stripe and the 402 Error Code
Author-email: Jonathan C <jonathan06891@gmail.com>
Project-URL: Homepage, https://github.com/Jonathan06891/django-api-gate
Project-URL: Bug Tracker, https://github.com/Jonathan06891/django-api-gate/issues
Classifier: Framework :: Django
Classifier: Programming Language :: Python :: 3
Classifier: License :: OSI Approved :: MIT License
Classifier: Operating System :: OS Independent
Classifier: Topic :: Internet :: WWW/HTTP :: Dynamic Content
Requires-Python: >=3.9
Requires-Dist: django>=4.0
Requires-Dist: requests
